README
setup.py
.hg/00changelog.i
.hg/branch
.hg/dirstate
.hg/hgrc
.hg/requires
src/QualysUtils.egg-info/PKG-INFO
src/QualysUtils.egg-info/SOURCES.txt
src/QualysUtils.egg-info/dependency_links.txt
src/QualysUtils.egg-info/requires.txt
src/QualysUtils.egg-info/top_level.txt
src/qualysutils/__init__.py