Metadata-Version: 1.0
Name: QualysUtils
Version: 0.0.1
Summary: uWaterloo QualysGuard(R) QualysUtils Package
Home-page: http://ist.uwaterloo.ca/iss/projects/qualysutils.html
Author: Colin Bell
Author-email: colin.bell@uwaterloo.ca
License: BSD-new
Keywords: Qualys QualysGuard API helper network security
Platform: UNKNOWN
Classifier: Development Status :: 3 - Alpha
Classifier: Topic :: Utilities
Classifier: License :: OSI Approved :: BSD License
